hubisModel/__init__.py
hubisModel/simple_module.py
hubisModel_pkg_yjko-0.0.1.dist-info/METADATA
hubisModel_pkg_yjko-0.0.1.dist-info/WHEEL
hubisModel_pkg_yjko-0.0.1.dist-info/top_level.txt
hubisModel_pkg_yjko-0.0.1.dist-info/RECORD
