Metadata-Version: 2.1
Name: hubisModel-pkg-yjko
Version: 0.0.1
Summary: A small example package
Home-page: UNKNOWN
Author: yjko
Author-email: fft6804@gmail.com
License: UNKNOWN
Platform: UNKNOWN
Classifier: Programming Language :: Python :: 3
Classifier: License :: OSI Approved :: MIT License
Classifier: Operating System :: OS Independent
Requires-Python: >=3.5
